lab3B.v
module lab3B(A,B,Cin,sum,carry);
input A,B,Cin;
output sum,carry;
assign sum=A^B^Cin;
assign carry=(A&B)|(B&Cin)|(Cin&A);
endmodule

lab3B_tb.v
`timescale 1ns/1ns
`include "lab3B.v"
module lab3B_tb(); 
reg A,B,Cin;
wire sum,carry;
lab3B ab(A,B,Cin,sum,carry);
always@(A or B or Cin);
initial
begin
$dumpfile("lab3B_tb.vcd");
$dumpvars(0, lab3B_tb);
A=3'b0; B=3'b0; Cin=3'b0;
#20;
A=3'b0;B=3'b0;Cin=3'b0;
#20;
A=3'b0;B=3'b0;Cin=3'b1;
#20;
A=3'b0;B=3'b0;Cin=3'b1;
#20;
A=3'b0;B=3'b1;Cin=3'b0;
#20;
A=3'b0;B=3'b1;Cin=3'b0;
#20;
A=3'b0;B=3'b1;Cin=3'b1;
#20;
A=3'b0;B=3'b1;Cin=3'b1;
#20;
A=3'b1;B=3'b0;Cin=3'b0;
#20;
A=3'b1;B=3'b0;Cin=3'b0;
#20;
A=3'b1;B=3'b0;Cin=3'b1;
#20;
A=3'b1;B=3'b0;Cin=3'b1;
#20;
A=3'b1;B=3'b1;Cin=3'b0;
#20;
A=3'b0;B=3'b1;Cin=3'b0;
#20;
A=3'b1;B=3'b1;Cin=3'b1;
#20;
A=3'b1;B=3'b1;Cin=3'b1;
#20;
$display("Test Complete");
end
endmodule

lab3B_tb.vcd
$date
	Tue Aug  6 14:46:11 2024
$end
$version
	Icarus Verilog
$end
$timescale
	1ns
$end
$scope module lab3B_tb $end
$var wire 1 ! sum $end
$var wire 1 " carry $end
$var reg 1 # A $end
$var reg 1 $ B $end
$var reg 1 % Cin $end
$scope module ab $end
$var wire 1 # A $end
$var wire 1 $ B $end
$var wire 1 % Cin $end
$var wire 1 " carry $end
$var wire 1 ! sum $end
$upscope $end
$upscope $end
$enddefinitions $end
#0
$dumpvars
0%
0$
0#
0"
0!
$end
#40
1!
1%
#80
0%
1$
#120
1"
0!
1%
#160
0"
1!
0%
0$
1#
#200
1"
0!
1%
#240
0%
1$
#260
0"
1!
0#
#280
1"
1%
1#
