lab3A.v
module lab3A(A,B,C,D,f);
input A,B,C,D;
output f;
assign g=(~C&~D);
assign h=(~A&~B);
assign f=(g&h)|(~g&~h);
endmodule

lab3A_tb.v
`timescale 1ns/1ns
`include "lab3A.v"
module lab3A_tb(); 
reg A,B,C,D;
wire f;
lab3A ab(A,B,C,D,f);
initial
begin
$dumpfile("lab3A_tb.vcd");
$dumpvars(0, lab3A_tb);
A=1'b0; B=1'b0; C=1'b0; D=1'b0;
#20;
A=1'b0;B=1'b0;C=1'b0;D=1'b1;
#20;
A=1'b0;B=1'b0;C=1'b1;D=1'b0;
#20;
A=1'b0;B=1'b0;C=1'b1;D=1'b1;
#20;
A=1'b0;B=1'b1;C=1'b0;D=1'b0;
#20;
A=1'b0;B=1'b1;C=1'b0;D=1'b1;
#20;
A=1'b0;B=1'b1;C=1'b1;D=1'b0;
#20;
A=1'b0;B=1'b1;C=1'b1;D=1'b1;
#20;
A=1'b1;B=1'b0;C=1'b0;D=1'b0;
#20;
A=1'b1;B=1'b0;C=1'b0;D=1'b1;
#20;
A=1'b1;B=1'b0;C=1'b1;D=1'b0;
#20;
A=1'b1;B=1'b0;C=1'b1;D=1'b1;
#20;
A=1'b1;B=1'b1;C=1'b0;D=1'b0;
#20;
A=1'b0;B=1'b1;C=1'b0;D=1'b1;
#20;
A=1'b1;B=1'b1;C=1'b1;D=1'b0;
#20;
A=1'b1;B=1'b1;C=1'b1;D=1'b1;
#20;
$display("Test Complete");
end
endmodule

lab3A_tb.vcd
$date
	Tue Aug  6 14:46:20 2024
$end
$version
	Icarus Verilog
$end
$timescale
	1ns
$end
$scope module lab3A_tb $end
$var wire 1 ! f $end
$var reg 1 " A $end
$var reg 1 # B $end
$var reg 1 $ C $end
$var reg 1 % D $end
$scope module ab $end
$var wire 1 " A $end
$var wire 1 # B $end
$var wire 1 $ C $end
$var wire 1 % D $end
$var wire 1 ! f $end
$var wire 1 & g $end
$var wire 1 ' h $end
$upscope $end
$upscope $end
$enddefinitions $end
#0
$dumpvars
1'
1&
0%
0$
0#
0"
1!
$end
#20
0!
0&
1%
#40
0%
1$
#60
1%
#80
1&
0'
0%
0$
1#
#100
1!
0&
1%
#120
0%
1$
#140
1%
#160
0!
1&
0%
0$
0#
1"
#180
1!
0&
1%
#200
0%
1$
#220
1%
#240
0!
1&
0%
0$
1#
#260
1!
0&
1%
0"
#280
0%
1$
1"
#300
1%
